[
  {
    "id": 1,
    "name": "moodle",
    "difficulty": 2,

  },
  {
    "id": 2,
    "name": "Italc",
    "difficulty": 2,

  },
  {
    "id": 3,
    "name": "ICRS",
    "difficulty": 2,
  },
  {
    "id": 4,
    "name": "Big Blue Button",
    "difficulty": 1,
    "collaboration":{
        "real-time": "real-time converstation"
        "video-conferencing": "Have video conferences with your peers"
        "text": false,
        "multimedia": "Allows mutlimedia aspects such as sharing images, annotating said items that are being shared"
        "engagement": "Video conferencing mixed with multimedia aspects have been known to cause "
        "sharing": false,
        "schedule": false,
    },
    "Alternative Technology": [
        "Skype"
    ]
  },
  {
    "id": 5,
    "name": "GeoPDF",
    "difficulty": 1,
  },
  {
    "id": 6,
    "name": "OneNote"
    "difficulty": 1,
  },
  {
    "id": 7,
    "name": "Word"
    "difficulty": 1,
  },
  {
    "id": 8,
    "name": "PowerPoint"
    "difficulty": 1,
  },
  {
    "id": 9,
    "name": "EtherPad",
    "difficulty": 1,
    "collaboration": {
      "real-time": "Edit documents at the same time and never be afraid of whether you have the latest edit"
      "video-conferencing": false,
      "text": "Type up information",
      "multimedia": false,
      "engagement": false,
      "sharing": "No longer having to send out the same document to your peers over and over again",
      "schedule": "A team member can still catch up even if he wasn't there then"
    },
    "Alternative Technology": [
        "Skype"
    ]

  },
  {
    "id": 10,
    "name": "ScreenSharing"
    "difficulty": 1,
    "collaboration":{
      "real-time": ,
      "video-conferencing":,
      "text"
      "multimedia":,
      "engagement":,
      "sharing":,
      "schedule":,
}

  },
  {
    "id": 1,
    "name": "The Flying Falafel",
    "rating": 4.3,
    "review_count": 341,
    "url": "http://www.yelp.com/biz/the-flying-falafel-san-francisco-3",
    "categories": [
      "Falafel",
      "Vegan",
      "Gluten-Free"
    ],
    "address": "1051 Market St, SoMa, San Francisco, CA 94103",
    "coordinate": {
      "latitude": 37.78125,
      "longitude": -122.4113007
    },
    "description": "Yep, this place is a winner! \n\nFalafel pocket sandwich overflowing with goodness- falafel balls (sesame or spicy), veggies (~6 options), and sauces (~4...",
    "is_closed": true,
    "phone": "+1-415-964-1003"
  }
]
